{"at": "2026-07-16T01:55:15.458610Z", "fatal_hits": [], "mismatched": [], "missing": [], "processes": {"binance_data_fusion": {"cpu_ticks_delta": 30138, "pid": 4161687, "start_time_ticks": 1132986750, "state": "S"}, "bitget_data_fusion": {"cpu_ticks_delta": 30132, "pid": 4161688, "start_time_ticks": 1132986750, "state": "S"}, "feedback": {"cpu_ticks_delta": 6118, "pid": 4162203, "start_time_ticks": 1132995214, "state": "R"}, "gateway": {"cpu_ticks_delta": 6120, "pid": 4162204, "start_time_ticks": 1132995214, "state": "S"}, "guard": {"cpu_ticks_delta": 1, "pid": 4162539, "start_time_ticks": 1132999963, "state": "S"}, "strategy": {"cpu_ticks_delta": 6120, "pid": 4162543, "start_time_ticks": 1132999986, "state": "R"}}, "result": "ok"}
