{"errors": {}, "ok": true, "results": {"order_info": {"code": "00000", "data": {"amount": "0", "avgPrice": "0.30692", "cancelReason": "", "category": "USDT-FUTURES", "clientOid": "a-432345564227567631", "createdTime": "1784121829237", "cumExecQty": "17", "cumExecValue": "5.2176", "delegateType": "normal", "execType": "normal", "feeDetail": [{"fee": "0.00104352", "feeCoin": "USDT"}], "holdMode": "one_way_mode", "marginMode": "crossed", "orderId": "1461278352859607041", "orderStatus": "filled", "orderType": "limit", "posSide": "long", "price": "0.30692", "qty": "17", "reduceOnly": "YES", "side": "buy", "slLimitPrice": null, "slOrderType": null, "slTriggerBy": null, "stopLoss": null, "stpMode": "none", "symbol": "RAVEUSDT", "takeProfit": null, "timeInForce": "ioc", "tpLimitPrice": null, "tpOrderType": null, "tpTriggerBy": null, "tradeSide": "buy_single", "updatedTime": "1784121829239"}, "msg": "success", "requestTime": 1784122870610}}}
